{
  "emotional_analysis": {
    "affective_words": [
      {
        "word": "tense",
        "confidence": 90
      },
      {
        "word": "hostile",
        "confidence": 88
      },
      {
        "word": "alarming",
        "confidence": 85
      },
      {
        "word": "conflict-ridden",
        "confidence": 82
      },
      {
        "word": "urgent",
        "confidence": 78
      },
      {
        "word": "somber",
        "confidence": 75
      },
      {
        "word": "volatile",
        "confidence": 70
      }
    ]
  }
}