{
  "emotional_analysis": {
    "affective_words": [
      {
        "word": "alarming",
        "confidence": 90
      },
      {
        "word": "distressing",
        "confidence": 85
      },
      {
        "word": "dire",
        "confidence": 80
      },
      {
        "word": "concerning",
        "confidence": 75
      },
      {
        "word": "urgent",
        "confidence": 80
      },
      {
        "word": "threatening",
        "confidence": 75
      },
      {
        "word": "grave",
        "confidence": 80
      }
    ]
  }
}