{
  "emotional_analysis": {
    "affective_words": [
      {
        "word": "concerning",
        "confidence": 90
      },
      {
        "word": "deteriorating",
        "confidence": 85
      },
      {
        "word": "unequal",
        "confidence": 82
      },
      {
        "word": "tense",
        "confidence": 78
      },
      {
        "word": "alarming",
        "confidence": 75
      },
      {
        "word": "disheartening",
        "confidence": 70
      },
      {
        "word": "divisive",
        "confidence": 68
      }
    ]
  }
}