{
  "emotional_analysis": {
    "affective_words": [
      {
        "word": "quiet",
        "confidence": 90
      },
      {
        "word": "suspicious",
        "confidence": 85
      },
      {
        "word": "tense",
        "confidence": 80
      },
      {
        "word": "controversial",
        "confidence": 78
      },
      {
        "word": "ominous",
        "confidence": 75
      },
      {
        "word": "restrained",
        "confidence": 72
      },
      {
        "word": "critical",
        "confidence": 70
      },
      {
        "word": "defensive",
        "confidence": 65
      }
    ]
  }
}