{
  "emotional_analysis": {
    "affective_words": [
      {
        "word": "concerned",
        "confidence": 85
      },
      {
        "word": "surprising",
        "confidence": 80
      },
      {
        "word": "alarming",
        "confidence": 78
      },
      {
        "word": "serious",
        "confidence": 75
      },
      {
        "word": "worrying",
        "confidence": 72
      },
      {
        "word": "disturbing",
        "confidence": 70
      },
      {
        "word": "significant",
        "confidence": 65
      },
      {
        "word": "global",
        "confidence": 60
      }
    ]
  }
}