{
  "emotional_analysis": {
    "affective_words": [
      {
        "word": "ominous",
        "confidence": 90
      },
      {
        "word": "worried",
        "confidence": 85
      },
      {
        "word": "concerned",
        "confidence": 82
      },
      {
        "word": "anxious",
        "confidence": 78
      },
      {
        "word": "uncertain",
        "confidence": 75
      },
      {
        "word": "foreboding",
        "confidence": 73
      },
      {
        "word": "serious",
        "confidence": 70
      },
      {
        "word": "cautious",
        "confidence": 65
      }
    ]
  }
}