{
  "emotional_analysis": {
    "affective_words": [
      {
        "word": "controversial",
        "confidence": 90
      },
      {
        "word": "defensive",
        "confidence": 85
      },
      {
        "word": "pressured",
        "confidence": 80
      },
      {
        "word": "transformative",
        "confidence": 75
      },
      {
        "word": "critical",
        "confidence": 78
      },
      {
        "word": "resistant",
        "confidence": 72
      },
      {
        "word": "strategic",
        "confidence": 68
      },
      {
        "word": "reformative",
        "confidence": 65
      }
    ]
  }
}