{
  "emotional_analysis": {
    "affective_words": [
      {
        "word": "hopeful",
        "confidence": 85
      },
      {
        "word": "progressive",
        "confidence": 80
      },
      {
        "word": "scientific",
        "confidence": 75
      },
      {
        "word": "historic",
        "confidence": 78
      },
      {
        "word": "triumphant",
        "confidence": 70
      },
      {
        "word": "cautious",
        "confidence": 65
      },
      {
        "word": "innovative",
        "confidence": 82
      },
      {
        "word": "resilient",
        "confidence": 68
      }
    ]
  }
}