{
  "emotional_analysis": {
    "affective_words": [
      {
        "word": "concerned",
        "confidence": 88
      },
      {
        "word": "declining",
        "confidence": 85
      },
      {
        "word": "uncertain",
        "confidence": 82
      },
      {
        "word": "pressured",
        "confidence": 78
      },
      {
        "word": "resilient",
        "confidence": 75
      },
      {
        "word": "strategic",
        "confidence": 70
      },
      {
        "word": "vulnerable",
        "confidence": 68
      },
      {
        "word": "cautious",
        "confidence": 72
      }
    ]
  }
}