{
  "emotional_analysis": {
    "affective_words": [
      {
        "word": "concerned",
        "confidence": 90
      },
      {
        "word": "alarming",
        "confidence": 85
      },
      {
        "word": "urgent",
        "confidence": 80
      },
      {
        "word": "worried",
        "confidence": 78
      },
      {
        "word": "serious",
        "confidence": 75
      },
      {
        "word": "distressing",
        "confidence": 72
      },
      {
        "word": "growing",
        "confidence": 68
      },
      {
        "word": "troubling",
        "confidence": 70
      }
    ]
  }
}