{
  "emotional_analysis": {
    "affective_words": [
      {
        "word": "concerned",
        "confidence": 88
      },
      {
        "word": "alarming",
        "confidence": 85
      },
      {
        "word": "overwhelming",
        "confidence": 80
      },
      {
        "word": "urgent",
        "confidence": 78
      },
      {
        "word": "critical",
        "confidence": 75
      },
      {
        "word": "somber",
        "confidence": 72
      },
      {
        "word": "motivating",
        "confidence": 65
      },
      {
        "word": "accountable",
        "confidence": 60
      }
    ]
  }
}