{
  "emotional_analysis": {
    "affective_words": [
      {
        "word": "concerned",
        "confidence": 85
      },
      {
        "word": "pressured",
        "confidence": 80
      },
      {
        "word": "frustrated",
        "confidence": 75
      },
      {
        "word": "anxious",
        "confidence": 70
      },
      {
        "word": "burdened",
        "confidence": 65
      },
      {
        "word": "disappointed",
        "confidence": 60
      },
      {
        "word": "weary",
        "confidence": 55
      }
    ]
  }
}