{
  "emotional_analysis": {
    "affective_words": [
      {
        "word": "impressive",
        "confidence": 90
      },
      {
        "word": "dominant",
        "confidence": 85
      },
      {
        "word": "strategic",
        "confidence": 80
      },
      {
        "word": "powerful",
        "confidence": 78
      },
      {
        "word": "surprising",
        "confidence": 75
      },
      {
        "word": "valuable",
        "confidence": 82
      },
      {
        "word": "confident",
        "confidence": 70
      },
      {
        "word": "competitive",
        "confidence": 65
      }
    ]
  }
}